[
    {
        "name": "午门",
        "lat": 39.9121168,
        "lng": 116.3915912,
        "image": "img/wumen.jpg",
        "details": "午门是故宫的正门，好像皇帝的“欢迎大门”。很多游客从这里进去，象征着进入皇宫的神秘世界。",
        "pose": "站在门前，双手举成‘V’形，笑着仰望城楼，像是要进入皇宫的勇士！",
        "animal": "麒麟"
    },
    {
        "name": "太和门",
        "lat": 39.914015503041625,
        "lng": 116.39087677001955,
        "image": "img/taihemen.jpg",
        "details": "太和门连接外朝和内廷，是个重要的过渡门，好像从“开会大厅”进入“家庭区域”的门。",
        "pose": "双手自然下垂，身体微微前倾，摆出‘请进’的姿势，像小小宫门守卫！",
        "animal": "獬豸"
    },
    {
        "name": "太和殿",
        "lat": 39.9159377,
        "lng": 116.3908125,
        "image": "img/taihedian.jpg",
        "details": "太和殿是举行大典的地方，皇帝在这里站在最高处，好像整个中国的“舞台中心”。",
        "pose": "双手叉腰、抬头挺胸，摆出‘我是小皇帝’的气势姿势！",
        "animal": "龙"
    },
    {
        "name": "中和殿",
        "lat": 39.9164758,
        "lng": 116.3907906,
        "image": "img/zhonghedian.jpg",
        "details": "中和殿有点像皇帝稍作休息或准备的地方，是“太和殿”的小助手。",
        "pose": "双手合十放胸前，闭眼微笑，像在冥想一样‘保持平衡与中和’。",
        "animal": "貔貅"
    },
    {
        "name": "保和殿",
        "lat": 39.9170044,
        "lng": 116.3907697,
        "image": "img/baohedian.jpg",
        "details": "保和殿用来考取功名和举行宴会，皇帝和大臣们在这里“开派对＋考试”。",
        "pose": "举起一本书或手比‘OK’，做出‘考试顺利’的姿势！",
        "animal": "凤"
    },
    {
        "name": "乾清宫",
        "lat": 39.9187857,
        "lng": 116.3906648,
        "image": "img/qianqinggong.jpg",
        "details": "乾清宫是皇帝的寝宫，就像皇帝的“家”一样，安静、尊贵。",
        "pose": "一手叉腰，一手做‘请进’动作，像主人邀请客人来家里玩。",
        "animal": "白虎"
    },
    {
        "name": "交泰殿",
        "lat": 39.9190823,
        "lng": 116.3906455,
        "image": "img/jiaotaidian.jpg",
        "details": "交泰殿象征“天人交泰、皇室和谐”，就像皇帝和皇后相处的地方。",
        "pose": "和朋友面对面比心，代表‘和谐美满’！",
        "animal": "鸾鸟"
    },
    {
        "name": "坤宁宫",
        "lat": 39.9193567,
        "lng": 116.3906422,
        "image": "img/kunninggong.jpg",
        "details": "坤宁宫是皇后的寝宫，好像“皇后专属的房间”，美丽又庄重。",
        "pose": "一手提‘想象中的裙摆’，另一手轻轻比心，做个优雅‘小皇后’造型。",
        "animal": "朱雀"
    },
    {
        "name": "御花园",
        "lat": 39.9201848,
        "lng": 116.3906109,
        "image": "img/yuhuayuan.jpg",
        "details": "御花园是皇宫里的花园，有花、有树、有池塘，是皇帝和皇后散步聊天的地方，像个秘密花园。",
        "pose": "张开双臂转圈，或者蹲下闻花香，露出自然微笑～",
        "animal": "鹿"
    },
    {
        "name": "神武门",
        "lat": 39.9209364,
        "lng": 116.3905732,
        "image": "img/shenwumen.jpg",
        "details": "神武门是故宫的北门，好像皇宫的“后门”，象征结束了参观，走出历史的旅程。",
        "pose": "背对大门回头笑，做个‘告别皇宫’的俏皮姿势。",
        "animal": "玄武"
    },
    {
        "name": "九龙壁",
        "lat": 39.917101,
        "lng": 116.3941884,
        "image": "img/jiulongbi.jpg",
        "details": "九龙壁上雕刻着九条龙，好像皇帝的“专属龙队伍”，非常霸气。",
        "pose": "双手做出‘龙爪’动作，模仿喷火的表情，霸气登场！",
        "animal": "九龙"
    },
    {
        "name": "文华殿",
        "lat": 39.9142984,
        "lng": 116.3930724,
        "image": "img/wenhuadian.jpg",
        "details": "文华殿是读书和写诗的地方，就像皇帝的“文艺沙龙”，充满书香气。",
        "pose": "拿出笔或假装写诗，皱眉沉思的‘小诗人’姿势！",
        "animal": "青鸾"
    },
    {
        "name": "武英殿",
        "lat": 39.9141774,
        "lng": 116.3883258,
        "image": "img/wuyingdian.jpg",
        "details": "武英殿保存着很多古书，被称为“皇家的图书馆”，知识满满。",
        "pose": "双手托腮，看向远方，像在思考‘今天读哪本书好呢？’",
        "animal": "狮子"
    },
    {
        "name": "养心殿",
        "lat": 39.9183568,
        "lng": 116.3894236,
        "image": "img/yangxindian.jpg",
        "details": "养心殿是皇帝晚年办公和生活的地方，好像皇帝的“办公室＋休息室”。",
        "pose": "手拿扇子，假装在批阅奏折，摆出‘认真办公’的模样。",
        "animal": "瑞兽貔貅"
    },
    {
        "name": "寿安宫",
        "lat": 39.91929838497778,
        "lng": 116.38740062713624,
        "image": "img/shouangong.jpg",
        "details": "寿安宫是太后居住的地方，好像皇家的“奶奶房间”，悠闲而庄重。",
        "pose": "双手合十放胸前，微笑祈福‘祝大家都平安长寿’。",
        "animal": "仙鹤"
    },
    {
        "name": "景仁宫",
        "lat": 39.9189086,
        "lng": 116.3917614,
        "image": "img/jingrengong.jpg",
        "details": "景仁宫是皇子妃们生活的地方，好像皇室大家庭里孩子们的“别墅区”。",
        "pose": "三五好友一起比心或拉手，像闺蜜合照一样温馨。",
        "animal": "玉兔"
    },
    {
        "name": "承乾宫",
        "lat": 39.9193638,
        "lng": 116.3917416,
        "image": "img/chengqiangong.jpg",
        "details": "承乾宫曾是皇子们朗读经典的地方，是未来帝王练习的“学堂”。",
        "pose": "拿出一本书或假装朗读，举手示意‘老师我会！’",
        "animal": "麒鹿"
    },
    {
        "name": "钟粹宫",
        "lat": 39.9198243,
        "lng": 116.3917165,
        "image": "img/zhongcuigong.jpg",
        "details": "钟粹宫是后宫的一部分，好像皇后的“闺房”，安静、典雅。",
        "pose": "双手托脸、甜甜微笑，做个‘温柔可爱’的公主姿势。",
        "animal": "凤凰雏"
    },
    {
        "name": "景阳宫",
        "lat": 39.9198344,
        "lng": 116.3923731,
        "image": "img/jingyanggong.jpg",
        "details": "景阳宫原来是皇后和妃子的寝宫之一，像个“姐妹们的房间集群”。",
        "pose": "和朋友并肩靠头笑，像姐妹间的秘密合照。",
        "animal": "白鹿"
    },
    {
        "name": "翊坤宫",
        "lat": 39.9193073,
        "lng": 116.3895484,
        "image": "img/yikungong.jpg",
        "details": "翊坤宫名字里的‘坤’代表“地”，意为皇后辅佐国家，好像“国家背后的女人”。",
        "pose": "一手比心、一手握拳，代表‘温柔又有力量’。",
        "animal": "玄狐"
    },
    {
        "name": "储秀宫",
        "lat": 39.9197724,
        "lng": 116.3895164,
        "image": "img/chuxiugong.jpg",
        "details": "储秀宫是培养宫中女子学习礼仪的地方，就像“小公主学校”。",
        "pose": "摆出‘优雅行礼’的动作，抬下巴、微笑。",
        "animal": "孔雀"
    },
    {
        "name": "咸福宫",
        "lat": 39.9197188,
        "lng": 116.3888754,
        "image": "img/xianfugong.jpg",
        "details": "咸福宫名字里“咸福”表示“共有的福气”，在这里住的妃子希望福气一起分享。",
        "pose": "双手举高比心，对着镜头喊‘一起幸福！’",
        "animal": "瑞狮"
    },
    {
        "name": "永寿宫",
        "lat": 39.9188429,
        "lng": 116.3895608,
        "image": "img/yongshougong.jpeg",
        "details": "永寿宫名字里的“永寿”意味着“永远长寿”，是希望皇室代代安康的寓意。",
        "pose": "双手比‘寿’字形状或双手抱拳，微笑祝福大家健康长寿。",
        "animal": "龟"
    },
    {
        "name": "长春宫",
        "lat": 39.9192817,
        "lng": 116.3888927,
        "image": "img/changchungong.jpg",
        "details": "长春宫名字里“长春”意为“长久春天”，好像皇家的“青春常在”房间。",
        "pose": "跳起或伸手指向天空，摆出‘青春活力’的姿势！",
        "animal": "青龙"
    },
    {
        "name": "启祥门",
        "lat": 39.91859896139837,
        "lng": 116.38900995254518,
        "image": "img/qixianggong.jpg",
        "details": "启祥宫的“启祥”含义是“开启祥瑞”，像个“好运起点”的房间。",
        "pose": "手指向前方，做出‘出发好运！’的表情与动作。",
        "animal": "瑞凤"
    },
    {
        "name": "慈宁宫",
        "lat": 39.9164603,
        "lng": 116.3877498,
        "image": "img/cininggong.jpg",
        "details": "慈宁宫是太后住的地方，“慈宁”意味着慈爱与安宁，像皇室的“养老院”。",
        "pose": "双手抱肩，温柔地笑，摆出‘慈祥奶奶’的表情。",
        "animal": "白鹤"
    },
    {
        "name": "隆宗门",
        "lat": 39.9173924,
        "lng": 116.3894472,
        "image": "img/longzongmen.jpg",
        "details": "隆宗门是通往皇室后院的门，好像“皇家的内门”，平时不太被游客看到。",
        "pose": "双手推门状，做出‘偷偷探秘’的可爱动作。",
        "animal": "辟邪"
    },
    {
        "name": "体仁阁",
        "lat": 39.9149543,
        "lng": 116.3920284,
        "image": "img/tirengong.jpg",
        "details": "体仁阁曾是皇帝学习的地方，“体仁”意为“修身养性”，像个“学院”一样。",
        "pose": "手拿‘假书’，一边翻页一边眨眼，摆出‘聪明学习中’的样子。",
        "animal": "文麒麟"
    },
    {
        "name": "弘义阁",
        "lat": 39.9148661,
        "lng": 116.3896516,
        "image": "img/hongyige.jpg",
        "details": "弘义阁保存着古代书籍和典籍，是皇家的“图书馆＋藏书楼”。",
        "pose": "双手比‘书’的形状（合掌打开），摆出‘知识就是力量’的样子！",
        "animal": "玄鹤"
    },
    {
        "name": "东华门",
        "lat": 39.9135937,
        "lng": 116.3952057,
        "image": "img/donghuamen.jpg",
        "details": "东华门是故宫东侧的一道门，好像“侧门出口”，走这里可以看到不一样的风景。",
        "pose": "一手比‘再见’手势，一手指向门口，做个开心的告别动作。",
        "animal": "青龙守门"
    }
]